clearn/__init__.py
clearn/utils.py
clearn/classifier/__init__.py
clearn/classifier/classifier.py
clearn/classifier/utils.py
clearn/classifier/viz_utils.py
clearn/clustering/__init__.py
clearn/clustering/clustering.py
clearn/clustering/table_utils.py
clearn/clustering/utils.py
clearn/clustering/viz_utils.py
clearn/data_preprocessing/__init__.py
clearn/data_preprocessing/data_preprocessing.py
clearn/data_preprocessing/viz_utils.py
clearn/dimensionality_reduction/__init__.py
clearn/dimensionality_reduction/dimensionality_reduction.py
clearn/dimensionality_reduction/table_utils.py
clearn/dimensionality_reduction/utils.py
clearn/dimensionality_reduction/viz_utils.py
tests/__init__.py
tests/test_clearn.py
clust_learn-0.2.7.dist-info/LICENSE
clust_learn-0.2.7.dist-info/METADATA
clust_learn-0.2.7.dist-info/WHEEL
clust_learn-0.2.7.dist-info/top_level.txt
clust_learn-0.2.7.dist-info/RECORD
