Metadata-Version: 2.1
Name: clust-learn
Version: 0.2.7
Summary: A Python package for explainable cluster analysis
Home-page: https://github.com/malgar/clust-learn
Author: Miguel Alvarez-Garcia, Raquel Ibar-Alonso, Mar Arenas-Parra
Author-email: Miguel Alvarez-Garcia <malvarez.statistics@gmail.com>
License: GPLv3
Project-URL: Homepage, https://github.com/malgar/clust-learn
Project-URL: Bug Tracker, https://github.com/malgar/clust-learn/issues
Classifier: Programming Language :: Python :: 3
Classifier: License :: OSI Approved :: GNU General Public License v3 (GPLv3)
Classifier: Topic :: Scientific/Engineering
Classifier: Programming Language :: Python :: 3.9
Classifier: Programming Language :: Python :: 3.10
Classifier: Programming Language :: Python :: 3.11
Requires-Python: >=3.9
License-File: LICENSE
Requires-Dist: imbalanced-learn>=0.10.0
Requires-Dist: kneed>=0.7.0
Requires-Dist: matplotlib>=3.4.3
Requires-Dist: networkx>=2.6.3
Requires-Dist: numpy>=1.20.3
Requires-Dist: pandas<2.0,>=1.3.4
Requires-Dist: pingouin>=0.5.3
Requires-Dist: prince==0.10.4
Requires-Dist: scikit-learn>=1.0.2
Requires-Dist: scipy>=1.7.1
Requires-Dist: seaborn>=0.11.2
Requires-Dist: shap>=0.40.0
Requires-Dist: statsmodels>=0.13.2
Requires-Dist: xgboost>=1.5.2
